bci_ml/__init__.py
bci_ml/base_models.py
bci_ml-0.0.2.dist-info/LICENSE
bci_ml-0.0.2.dist-info/METADATA
bci_ml-0.0.2.dist-info/WHEEL
bci_ml-0.0.2.dist-info/top_level.txt
bci_ml-0.0.2.dist-info/RECORD
