Metadata-Version: 2.1
Name: bci-ml
Version: 0.0.2
Summary: lib for signal decoding, python package
Home-page: https://github.com/intsystems/bci-ml
Author: Intelligent Systems
Author-email: mlalgorithms@gmail.com
License: MIT
License-File: LICENSE
Requires-Dist: numpy (>=1.19.0)
Requires-Dist: torch (>=1.10.0)
